{"Name":"History 3","Subject":"['poetry', 'art and entertainment', 'books and literature', 'visual art and design', 'painting']","Level":"Elementary School","Description":"Explore the Renaissance, and meet Petrarch, da Vinci, Michelangelo, Gutenberg, Galileo, and more.","Concepts":"['Florence', 'Michelangelo', 'Renaissance', 'Tuscany', 'Italy', 'Leonardo da Vinci', 'Milan', 'Polymath']","URL":"https://www.k12.com/elementary-school-courses.html#elementary-school/course-details/5b562b1fb809da2a85d46877/"}